setup.py
gimme/__init__.py
gimme/__main__.py
gimme/app.py
gimme/cache.py
gimme/controller.py
gimme/dotdict.py
gimme/engines.py
gimme/errors.py
gimme/generator.py
gimme/headers.py
gimme/middleware.py
gimme/renderers.py
gimme/request.py
gimme/response.py
gimme/routes.py
gimme/uri.py
gimme/wsgi.py
gimme.egg-info/PKG-INFO
gimme.egg-info/SOURCES.txt
gimme.egg-info/dependency_links.txt
gimme.egg-info/entry_points.txt
gimme.egg-info/requires.txt
gimme.egg-info/top_level.txt
gimme/ext/__init__.py
gimme/ext/session.py
gimme/parsers/__init__.py
gimme/parsers/accepted.py
gimme/parsers/contenttype.py
gimme/parsers/multipart.py
gimme/parsers/status.py
gimme/servers/__init__.py
gimme/servers/http/__init__.py
gimme/servers/http/connection.py
gimme/servers/http/headers.py
gimme/servers/http/modulemonitor.py
gimme/servers/http/server.py
gimme/servers/logger/__init__.py
gimme/servers/logger/logger.py
gimme/templates/errors/404.html
gimme/templates/errors/500.html
gimme/templates/errors/base.html
gimme/templates/errors/generic.html
gimme/templates/generator/app.fcgi
gimme/templates/generator/app.py
gimme/templates/generator/routes.py
gimme/templates/generator/controllers/__init__.py
gimme/templates/generator/controllers/root.py
gimme/templates/generator/views/root/catch_all.html
gimme/templates/generator/views/root/index.html