Metadata-Version: 1.1
Name: gimme
Version: 0.1.3
Summary: An ExpressJS-inspired web framework... in Python
Home-page: UNKNOWN
Author: Tim Radke
Author-email: countach74@gmail.com
License: MIT
Download-URL: https://github.com/countach74/gimme/tarball/master
Platform: UNKNOWN
